TestProjectLibrary/TestProjectLibrary.py
TestProjectLibrary/__init__.py
TestProjectLibrary/definitions.py
testproject_robot_library-0.65.2.dist-info/LICENSE
testproject_robot_library-0.65.2.dist-info/METADATA
testproject_robot_library-0.65.2.dist-info/WHEEL
testproject_robot_library-0.65.2.dist-info/top_level.txt
testproject_robot_library-0.65.2.dist-info/RECORD
