Metadata-Version: 2.1
Name: testproject-robot-library
Version: 0.65.2
Summary: TestProject.io Library for the Robot Framrwork
Home-page: https://testproject.io/selenium-appium-powered-sdk/
Author: TestProject
Author-email: contact@testproject.io
License: UNKNOWN
Platform: UNKNOWN
Classifier: Programming Language :: Python :: 3
Classifier: License :: OSI Approved :: Apache Software License
Classifier: Operating System :: OS Independent
Requires-Python: >=3.6
Requires-Dist: robotframework-seleniumlibrary (>=4.5.0)
Requires-Dist: testproject-python-sdk (>=0.63.19)
Requires-Dist: importlib-metadata (>=1.7.0)
Requires-Dist: packaging (>=20.4)
